pysmock/__init__.py
pysmock/__main__.py
pysmock/logger/__init__.py
pysmock/logger/logger.py
pysmock/models/APIRequest.py
pysmock/models/Callback.py
pysmock/models/Contact.py
pysmock/models/Info.py
pysmock/models/License.py
pysmock/models/MockSetup.py
pysmock/models/Param.py
pysmock/models/Request.py
pysmock/models/RequestParams.py
pysmock/models/Response.py
pysmock/models/__init__.py
pysmock/templates/code.py
pysmock/templates/flask_app.py
pysmock/utils/GenericFieldParser.py
pysmock/utils/ModelParser.py
pysmock/utils/__init__.py
pysmock-0.1.4.dist-info/LICENSE
pysmock-0.1.4.dist-info/METADATA
pysmock-0.1.4.dist-info/WHEEL
pysmock-0.1.4.dist-info/entry_points.txt
pysmock-0.1.4.dist-info/top_level.txt
pysmock-0.1.4.dist-info/RECORD
